ticktick/__init__.py
ticktick/api.py
ticktick/cache.py
ticktick/oauth2.py
ticktick/helpers/__init__.py
ticktick/helpers/constants.py
ticktick/helpers/hex_color.py
ticktick/helpers/time_methods.py
ticktick/managers/__init__.py
ticktick/managers/check_logged_in.py
ticktick/managers/focus.py
ticktick/managers/habits.py
ticktick/managers/pomo.py
ticktick/managers/projects.py
ticktick/managers/settings.py
ticktick/managers/tags.py
ticktick/managers/tasks.py
ticktick_py-2.0.3.dist-info/LICENSE
ticktick_py-2.0.3.dist-info/METADATA
ticktick_py-2.0.3.dist-info/WHEEL
ticktick_py-2.0.3.dist-info/top_level.txt
ticktick_py-2.0.3.dist-info/RECORD
