Metadata-Version: 2.1
Name: ticktick-py
Version: 2.0.3
Summary: Unofficial API for TickTick.com
Home-page: https://github.com/lazeroffmichael/ticktick-py
Author: Michael Lazeroff
Author-email: lazeroffmichael@gmail.com
License: MIT
Classifier: License :: OSI Approved :: MIT License
Classifier: Programming Language :: Python
Classifier: Programming Language :: Python :: 3
Classifier: Programming Language :: Python :: 3.6
Classifier: Programming Language :: Python :: 3.7
Classifier: Programming Language :: Python :: 3.8
Classifier: Programming Language :: Python :: 3.9
Classifier: Programming Language :: Python :: Implementation :: CPython
Classifier: Programming Language :: Python :: Implementation :: PyPy
Classifier: Operating System :: OS Independent
Requires-Python: >=3.6.0
License-File: LICENSE
Requires-Dist: requests (==2.26.0)
Requires-Dist: pytz (==2021.1)
Requires-Dist: regex (==2021.4.4)
Requires-Dist: urllib3 (==1.26.7)
Provides-Extra: tests
Requires-Dist: pytest ; extra == 'tests'
